richprint/__init__.py
richprint/config.py
richprint/core.py
richprint/decorators.py
richprint/utils.py
tests/__init__.py
tests/test.py
richprint-0.1.0.dist-info/METADATA
richprint-0.1.0.dist-info/WHEEL
richprint-0.1.0.dist-info/top_level.txt
richprint-0.1.0.dist-info/RECORD
